llama/__init__.py
llama/metrics/compare_equal_metric.py
llama/metrics/metric.py
llama/program/builder.py
llama/program/function.py
llama/program/program.py
llama/program/value.py
llama/program/operations/batch_llama_operation.py
llama/program/operations/call_operation.py
llama/program/operations/feedback_operation.py
llama/program/operations/get_argument_operation.py
llama/program/operations/get_element_operation.py
llama/program/operations/get_field_operation.py
llama/program/operations/llama_operation.py
llama/program/operations/metric_operation.py
llama/program/operations/return_operation.py
llama/program/util/config.py
llama/program/util/run_ai.py
llama/program/util/type_to_dict.py
llama/types/base_specification.py
llama/types/context.py
llama/types/type.py
llama_llm-0.0.15.dist-info/LICENSE
llama_llm-0.0.15.dist-info/METADATA
llama_llm-0.0.15.dist-info/WHEEL
llama_llm-0.0.15.dist-info/top_level.txt
llama_llm-0.0.15.dist-info/RECORD
