Metadata-Version: 2.1
Name: llama-llm
Version: 0.0.15
Summary: Build on large language models faster
Author-email: PowerML <info@powerml.co>
Classifier: Programming Language :: Python :: 3
Classifier: License :: OSI Approved :: Apache Software License
Classifier: Operating System :: OS Independent
Requires-Python: >=3.7
License-File: LICENSE
Requires-Dist: pydantic
Requires-Dist: python-configuration[yaml]
Requires-Dist: requests
Requires-Dist: tokenizers
Requires-Dist: tqdm
Requires-Dist: numpy
Requires-Dist: scikit-learn
